coopgraph/__init__.py
coopgraph/api_utils.py
coopgraph/draw.py
coopgraph/graph_definitions.py
coopgraph/graphs.py
coopgraph/gridgraph.py
coopgraph-1.13.dist-info/LICENSE
coopgraph-1.13.dist-info/METADATA
coopgraph-1.13.dist-info/WHEEL
coopgraph-1.13.dist-info/top_level.txt
coopgraph-1.13.dist-info/RECORD
